ddex/__init__.py
ddex/const.py
ddex/ddex.py
ddex/exc.py
ddex/py.typed
ddex-0.0.1.dist-info/LICENSE
ddex-0.0.1.dist-info/WHEEL
ddex-0.0.1.dist-info/METADATA
ddex-0.0.1.dist-info/RECORD
